[
    {
      "Nom_complet": "ACHAHBAR Adam",
      "Archi Dis": "17,00",
      "Dot_Net": "15,80",
      "Adroide": "13,00",
      "Gest Proj": "11,00",
      "Pr Tutore": "17,50",
      "Data Mining": "11,00",
      "Data Warehouse": "11,67",
      "Moyenne Data Mining et Data Warehouse": "11,34",
      "Resultat Semestre « S2 »": "Validé",
      "Moyenne S1": "14,59",
      "Moyenne S2": "14,27",
      "Moyenne_annuelle": "14,43",
      "Resultat Année": "Année Validée" 
    },
    {
      "Nom_complet": "AHIZOUN Meriem",
      "Archi Dis": "20,00",
      "Dot_Net": "18,00",
      "Adroide": "18,00",
      "Gest Proj": "17,00",
      "Pr Tutore": "16,25",
      "Data Mining": "18,00",
      "Data Warehouse": "14,50",
      "Moyenne Data Mining et Data Warehouse": "16,25",
      "Resultat Semestre « S2 »": "Validé",
      "Moyenne S1": "18,75",
      "Moyenne S2": "17,58",
      "Moyenne_annuelle": "18,17",
      "Resultat Année": "Année Validée" 
    },
    {
      "Nom_complet": "AISSAOUI Rania",
      "Archi Dis": "14,00",
      "Dot_Net": "15,80",
      "Adroide": "16,00",
      "Gest Proj": "15,00",
      "Pr Tutore": "11,50",
      "Data Mining": "18,00",
      "Data Warehouse": "14,92",
      "Moyenne Data Mining et Data Warehouse": "16,46",
      "Resultat Semestre « S2 »": "Validé",
      "Moyenne S1": "14,03",
      "Moyenne S2": "14,79",
      "Moyenne_annuelle": "14,41",
      "Resultat Année": "Année Validée" 
    },
    {
      "Nom_complet": "AIT KHOYA Noureddine",
      "Archi Dis": "10,00",
      "Dot_Net": "15,60",
      "Adroide": "12,00",
      "Gest Proj": "11,00",
      "Pr Tutore": "11,00",
      "Data Mining": "11,00",
      "Data Warehouse": "10,00",
      "Moyenne Data Mining et Data Warehouse": "10,50",
      "Resultat Semestre « S2 »": "Validé",
      "Moyenne S1": "11,67",
      "Moyenne S2": "11,68",
      "Moyenne_annuelle": "11,68",
      "Resultat Année": "Année Validée" 
    },
    {
      "Nom_complet": "AMJAHID Mohamed Amine",
      "Archi Dis": "19,00",
      "Dot_Net": "17,40",
      "Adroide": "19,00",
      "Gest Proj": "18,00",
      "Pr Tutore": "16,50",
      "Data Mining": "19,00",
      "Data Warehouse": "17,67",
      "Moyenne Data Mining et Data Warehouse": "18,34",
      "Resultat Semestre « S2 »": "Validé",
      "Moyenne S1": "18,25",
      "Moyenne S2": "18,04",
      "Moyenne_annuelle": "18,14",
      "Resultat Année": "Année Validée" 
    },
    {
      "Nom_complet": "BADANE Mohammed",
      "Archi Dis": "16,00",
      "Dot_Net": "17,60",
      "Adroide": "15,00",
      "Gest Proj": "15,00",
      "Pr Tutore": "15,00",
      "Data Mining": "15,00",
      "Data Warehouse": "15,25",
      "Moyenne Data Mining et Data Warehouse": "15,13",
      "Resultat Semestre « S2 »": "Validé",
      "Moyenne S1": "16,42",
      "Moyenne S2": "15,62",
      "Moyenne_annuelle": "16,02",
      "Resultat Année": "Année Validée" 
    },
    {
      "Nom_complet": "BARA Soukaina",
      "Archi Dis": "16,00",
      "Dot_Net": "15,80",
      "Adroide": "17,00",
      "Gest Proj": "14,00",
      "Pr Tutore": "16,50",
      "Data Mining": "17,50",
      "Data Warehouse": "14,58",
      "Moyenne Data Mining et Data Warehouse": "16,04",
      "Resultat Semestre « S2 »": "Validé",
      "Moyenne S1": "15,62",
      "Moyenne S2": "15,89",
      "Moyenne_annuelle": "15,75",
      "Resultat Année": "Année Validée" 
    },
    {
      "Nom_complet": "BASLAM Ismail",
      "Archi Dis": "15,00",
      "Dot_Net": "16,00",
      "Adroide": "14,00",
      "Gest Proj": "11,00",
      "Pr Tutore": "14,00",
      "Data Mining": "14,00",
      "Data Warehouse": "11,00",
      "Moyenne Data Mining et Data Warehouse": "12,50",
      "Resultat Semestre « S2 »": "Validé",
      "Moyenne S1": "15,03",
      "Moyenne S2": "13,75",
      "Moyenne_annuelle": "14,39",
      "Resultat Année": "Année Validée" 
    },
    {
      "Nom_complet": "BASSIM Makram",
      "Archi Dis": "18,00",
      "Dot_Net": "15,20",
      "Adroide": "15,00",
      "Gest Proj": "16,00",
      "Pr Tutore": "14,00",
      "Data Mining": "11,00",
      "Data Warehouse": "12,08",
      "Moyenne Data Mining et Data Warehouse": "11,54",
      "Resultat Semestre « S2 »": "Validé",
      "Moyenne S1": "15,08",
      "Moyenne S2": "14,96",
      "Moyenne_annuelle": "15,02",
      "Resultat Année": "Année Validée" 
    },
    {
      "Nom_complet": "BEKKARI Meriem",
      "Archi Dis": "13,00",
      "Dot_Net": "11,50",
      "Adroide": "13,00",
      "Gest Proj": "11,00",
      "Pr Tutore": "13,00",
      "Data Mining": "11,00",
      "Data Warehouse": "10,00",
      "Moyenne Data Mining et Data Warehouse": "10,50",
      "Resultat Semestre « S2 »": "Validé",
      "Moyenne S1": "12,03",
      "Moyenne S2": "12,00",
      "Moyenne_annuelle": "12,02",
      "Resultat Année": "Année Validée" 
    },
    {
      "Nom_complet": "BELARBI Youssef",
      "Archi Dis": "13,00",
      "Dot_Net": "13,90",
      "Adroide": "12,00",
      "Gest Proj": "11,00",
      "Pr Tutore": "11,00",
      "Data Mining": "12,00",
      "Data Warehouse": "10,00",
      "Moyenne Data Mining et Data Warehouse": "11,00",
      "Resultat Semestre « S2 »": "Validé",
      "Moyenne S1": "12,50",
      "Moyenne S2": "11,98",
      "Moyenne_annuelle": "12,24",
      "Resultat Année": "Année Validée" 
    },
    {
      "Nom_complet": "BELAZIZ Ikhlas",
      "Archi Dis": "14,00",
      "Dot_Net": "14,60",
      "Adroide": "6,00",
      "Gest Proj": "12,00",
      "Pr Tutore": "12,00",
      "Data Mining": "13,00",
      "Data Warehouse": "8,00",
      "Moyenne Data Mining et Data Warehouse": "10,50",
      "Resultat Semestre « S2 »": "Validé avec Compensation",
      "Moyenne S1": "13,05",
      "Moyenne S2": "11,52",
      "Moyenne_annuelle": "12,28",
      "Resultat Année": "Année Validée" 
    },
    {
      "Nom_complet": "BENHAKKI Othmane",
      "Archi Dis": "17,00",
      "Dot_Net": "13,00",
      "Adroide": "14,00",
      "Gest Proj": "12,00",
      "Pr Tutore": "19,75",
      "Data Mining": "17,00",
      "Data Warehouse": "17,42",
      "Moyenne Data Mining et Data Warehouse": "17,21",
      "Resultat Semestre « S2 »": "Validé",
      "Moyenne S1": "17,03",
      "Moyenne S2": "15,49",
      "Moyenne_annuelle": "16,26",
      "Resultat Année": "Année Validée" 
    },
    {
      "Nom_complet": "BENMANSOUR Fatine",
      "Archi Dis": "14,00",
      "Dot_Net": "15,10",
      "Adroide": "14,00",
      "Gest Proj": "18,00",
      "Pr Tutore": "16,00",
      "Data Mining": "17,00",
      "Data Warehouse": "15,92",
      "Moyenne Data Mining et Data Warehouse": "16,46",
      "Resultat Semestre « S2 »": "Validé",
      "Moyenne S1": "14,00",
      "Moyenne S2": "15,59",
      "Moyenne_annuelle": "14,80",
      "Resultat Année": "Année Validée" 
    },
    {
      "Nom_complet": "BENNANI Abderrahman",
      "Archi Dis": "16,00",
      "Dot_Net": "15,60",
      "Adroide": "14,00",
      "Gest Proj": "15,00",
      "Pr Tutore": "13,50",
      "Data Mining": "12,00",
      "Data Warehouse": "12,67",
      "Moyenne Data Mining et Data Warehouse": "12,34",
      "Resultat Semestre « S2 »": "Validé",
      "Moyenne S1": "14,25",
      "Moyenne S2": "14,41",
      "Moyenne_annuelle": "14,33",
      "Resultat Année": "Année Validée" 
    },
    {
      "Nom_complet": "BENNANI Yassine",
      "Archi Dis": "17,00",
      "Dot_Net": "15,60",
      "Adroide": "16,00",
      "Gest Proj": "15,00",
      "Pr Tutore": "15,00",
      "Data Mining": "11,00",
      "Data Warehouse": "15,50",
      "Moyenne Data Mining et Data Warehouse": "13,25",
      "Resultat Semestre « S2 »": "Validé",
      "Moyenne S1": "14,80",
      "Moyenne S2": "15,31",
      "Moyenne_annuelle": "15,05",
      "Resultat Année": "Année Validée" 
    },
    {
      "Nom_complet": "BENNOUNA Ismail",
      "Archi Dis": "14,00",
      "Dot_Net": "11,00",
      "Adroide": "10,00",
      "Gest Proj": "11,00",
      "Pr Tutore": "11,00",
      "Data Mining": "12,00",
      "Data Warehouse": "10,00",
      "Moyenne Data Mining et Data Warehouse": "11,00",
      "Resultat Semestre « S2 »": "Validé",
      "Moyenne S1": "12,47",
      "Moyenne S2": "11,33",
      "Moyenne_annuelle": "11,90",
      "Resultat Année": "Année Validée" 
    },
    {
      "Nom_complet": "BENSLIMANE Amine",
      "Archi Dis": "16,00",
      "Dot_Net": "13,70",
      "Adroide": "15,00",
      "Gest Proj": "16,00",
      "Pr Tutore": "14,75",
      "Data Mining": "13,50",
      "Data Warehouse": "15,50",
      "Moyenne Data Mining et Data Warehouse": "14,50",
      "Resultat Semestre « S2 »": "Validé",
      "Moyenne S1": "14,05",
      "Moyenne S2": "14,99",
      "Moyenne_annuelle": "14,52",
      "Resultat Année": "Année Validée" 
    },
    {
      "Nom_complet": "BENTAHAR Zakariae",
      "Archi Dis": "19,00",
      "Dot_Net": "18,00",
      "Adroide": "18,00",
      "Gest Proj": "12,00",
      "Pr Tutore": "15,75",
      "Data Mining": "18,00",
      "Data Warehouse": "16,33",
      "Moyenne Data Mining et Data Warehouse": "17,17",
      "Resultat Semestre « S2 »": "Validé",
      "Moyenne S1": "18,37",
      "Moyenne S2": "16,65",
      "Moyenne_annuelle": "17,51",
      "Resultat Année": "Année Validée" 
    },
    {
      "Nom_complet": "BENYAHIA Khaoula",
      "Archi Dis": "14,00",
      "Dot_Net": "15,20",
      "Adroide": "15,00",
      "Gest Proj": "14,00",
      "Pr Tutore": "14,00",
      "Data Mining": "13,00",
      "Data Warehouse": "14,50",
      "Moyenne Data Mining et Data Warehouse": "13,75",
      "Resultat Semestre « S2 »": "Validé",
      "Moyenne S1": "14,47",
      "Moyenne S2": "14,33",
      "Moyenne_annuelle": "14,40",
      "Resultat Année": "Année Validée" 
    },
    {
      "Nom_complet": "BOUFTINI Mohammed",
      "Archi Dis": "13,00",
      "Dot_Net": "15,60",
      "Adroide": "13,00",
      "Gest Proj": "10,00",
      "Pr Tutore": "11,00",
      "Data Mining": "11,00",
      "Data Warehouse": "10,00",
      "Moyenne Data Mining et Data Warehouse": "10,50",
      "Resultat Semestre « S2 »": "Validé",
      "Moyenne S1": "12,13",
      "Moyenne S2": "12,18",
      "Moyenne_annuelle": "12,15",
      "Resultat Année": "Année Validée" 
    },
    {
      "Nom_complet": "BOURASSE Oussama",
      "Archi Dis": "17,00",
      "Dot_Net": "15,60",
      "Adroide": "15,00",
      "Gest Proj": "13,00",
      "Pr Tutore": "16,00",
      "Data Mining": "12,00",
      "Data Warehouse": "10,00",
      "Moyenne Data Mining et Data Warehouse": "11,00",
      "Resultat Semestre « S2 »": "Validé",
      "Moyenne S1": "16,33",
      "Moyenne S2": "14,60",
      "Moyenne_annuelle": "15,46",
      "Resultat Année": "Année Validée" 
    },
    {
      "Nom_complet": "BOUZIDI IDRISSI Oumayma",
      "Archi Dis": "15,00",
      "Dot_Net": "13,70",
      "Adroide": "14,00",
      "Gest Proj": "14,00",
      "Pr Tutore": "15,75",
      "Data Mining": "14,00",
      "Data Warehouse": "15,08",
      "Moyenne Data Mining et Data Warehouse": "14,54",
      "Resultat Semestre « S2 »": "Validé",
      "Moyenne S1": "13,51",
      "Moyenne S2": "14,50",
      "Moyenne_annuelle": "14,00",
      "Resultat Année": "Année Validée" 
    },
    {
      "Nom_complet": "CHAKIR Yassmine",
      "Archi Dis": "14,00",
      "Dot_Net": "13,00",
      "Adroide": "11,00",
      "Gest Proj": "13,00",
      "Pr Tutore": "14,00",
      "Data Mining": "13,00",
      "Data Warehouse": "13,00",
      "Moyenne Data Mining et Data Warehouse": "13,00",
      "Resultat Semestre « S2 »": "Validé",
      "Moyenne S1": "13,11",
      "Moyenne S2": "13,00",
      "Moyenne_annuelle": "13,06",
      "Resultat Année": "Année Validée" 
    },
    {
      "Nom_complet": "CHAOUI  Anass",
      "Archi Dis": "11,00",
      "Dot_Net": "11,50",
      "Adroide": "12,00",
      "Gest Proj": "11,00",
      "Pr Tutore": "12,25",
      "Data Mining": "11,00",
      "Data Warehouse": "11,00",
      "Moyenne Data Mining et Data Warehouse": "11,00",
      "Resultat Semestre « S2 »": "Validé",
      "Moyenne S1": "12,78",
      "Moyenne S2": "11,46",
      "Moyenne_annuelle": "12,12",
      "Resultat Année": "Année Validée" 
    },
    {
      "Nom_complet": "CHAOUNI BENABDELLAH EL Mehdi",
      "Archi Dis": "15,00",
      "Dot_Net": "15,60",
      "Adroide": "14,00",
      "Gest Proj": "13,00",
      "Pr Tutore": "18,00",
      "Data Mining": "11,00",
      "Data Warehouse": "10,00",
      "Moyenne Data Mining et Data Warehouse": "10,50",
      "Resultat Semestre « S2 »": "Validé",
      "Moyenne S1": "13,08",
      "Moyenne S2": "14,35",
      "Moyenne_annuelle": "13,72",
      "Resultat Année": "Année Validée" 
    },
    {
      "Nom_complet": "CHIBA Ismail",
      "Archi Dis": "16,00",
      "Dot_Net": "13,60",
      "Adroide": "12,00",
      "Gest Proj": "12,00",
      "Pr Tutore": "15,50",
      "Data Mining": "11,00",
      "Data Warehouse": "10,00",
      "Moyenne Data Mining et Data Warehouse": "10,50",
      "Resultat Semestre « S2 »": "Validé",
      "Moyenne S1": "14,04",
      "Moyenne S2": "13,27",
      "Moyenne_annuelle": "13,65",
      "Resultat Année": "Année Validée" 
    },
    {
      "Nom_complet": "DBIRA TLEMCANI  Hicham",
      "Archi Dis": "13,00",
      "Dot_Net": "13,00",
      "Adroide": "15,00",
      "Gest Proj": "13,00",
      "Pr Tutore": "16,50",
      "Data Mining": "13,00",
      "Data Warehouse": "10,00",
      "Moyenne Data Mining et Data Warehouse": "11,50",
      "Resultat Semestre « S2 »": "Validé",
      "Moyenne S1": "13,29",
      "Moyenne S2": "13,67",
      "Moyenne_annuelle": "13,48",
      "Resultat Année": "Année Validée" 
    },
    {
      "Nom_complet": "DHASSI Houda",
      "Archi Dis": "5,00",
      "Dot_Net": "11,60",
      "Adroide": "8,00",
      "Gest Proj": "11,00",
      "Pr Tutore": "11,50",
      "Data Mining": "13,00",
      "Data Warehouse": "10,00",
      "Moyenne Data Mining et Data Warehouse": "11,50",
      "Resultat Semestre « S2 »": "Semestre « S2 » non Validé",
      "Moyenne S1": "10,43",
      "Moyenne S2": "9,77",
      "Moyenne_annuelle": "10,10",
      "Resultat Année": "Année Validée par Compensation" 
    },
    {
      "Nom_complet": "DIONI Al Hassan",
      "Archi Dis": "12,00",
      "Dot_Net": "12,10",
      "Adroide": "14,00",
      "Gest Proj": "16,00",
      "Pr Tutore": "13,00",
      "Data Mining": "13,00",
      "Data Warehouse": "16,00",
      "Moyenne Data Mining et Data Warehouse": "14,50",
      "Resultat Semestre « S2 »": "Validé",
      "Moyenne S1": "13,13",
      "Moyenne S2": "13,60",
      "Moyenne_annuelle": "13,37",
      "Resultat Année": "Année Validée" 
    },
    {
      "Nom_complet": "DOBLI BENNANI Kamar",
      "Archi Dis": "18,00",
      "Dot_Net": "13,40",
      "Adroide": "15,50",
      "Gest Proj": "15,00",
      "Pr Tutore": "15,50",
      "Data Mining": "15,00",
      "Data Warehouse": "12,67",
      "Moyenne Data Mining et Data Warehouse": "13,84",
      "Resultat Semestre « S2 »": "Validé",
      "Moyenne S1": "16,12",
      "Moyenne S2": "15,21",
      "Moyenne_annuelle": "15,66",
      "Resultat Année": "Année Validée" 
    },
    {
      "Nom_complet": "DOUAHI Souhaila",
      "Archi Dis": "13,00",
      "Dot_Net": "12,00",
      "Adroide": "10,00",
      "Gest Proj": "11,00",
      "Pr Tutore": "11,50",
      "Data Mining": "12,00",
      "Data Warehouse": "9,00",
      "Moyenne Data Mining et Data Warehouse": "10,50",
      "Resultat Semestre « S2 »": "Validé",
      "Moyenne S1": "12,02",
      "Moyenne S2": "11,33",
      "Moyenne_annuelle": "11,68",
      "Resultat Année": "Année Validée" 
    },
    {
      "Nom_complet": "EDDAKI Taha",
      "Archi Dis": "16,00",
      "Dot_Net": "16,80",
      "Adroide": "16,00",
      "Gest Proj": "11,00",
      "Pr Tutore": "14,50",
      "Data Mining": "13,00",
      "Data Warehouse": "11,00",
      "Moyenne Data Mining et Data Warehouse": "12,00",
      "Resultat Semestre « S2 »": "Validé",
      "Moyenne S1": "15,43",
      "Moyenne S2": "14,38",
      "Moyenne_annuelle": "14,90",
      "Resultat Année": "Année Validée" 
    },
    {
      "Nom_complet": "EJ-JAIDI Aymane",
      "Archi Dis": "0,00",
      "Dot_Net": "0,00",
      "Adroide": "0,00",
      "Gest Proj": "0,00",
      "Pr Tutore": "0,00",
      "Data Mining": "0,00",
      "Data Warehouse": "0,00",
      "Moyenne Data Mining et Data Warehouse": "0,00",
      "Resultat Semestre « S2 »": "Semestre « S2 » non Validé",
      "Moyenne S1": "2,17",
      "Moyenne S2": "0,00",
      "Moyenne_annuelle": "1,08",
      "Resultat Année": "Ajourné" 
    },
    {
      "Nom_complet": "EL ABBADI Mohammed Amine",
      "Archi Dis": "10,00",
      "Dot_Net": "14,30",
      "Adroide": "14,50",
      "Gest Proj": "14,00",
      "Pr Tutore": "13,75",
      "Data Mining": "13,00",
      "Data Warehouse": "11,67",
      "Moyenne Data Mining et Data Warehouse": "12,34",
      "Resultat Semestre « S2 »": "Validé",
      "Moyenne S1": "14,08",
      "Moyenne S2": "13,15",
      "Moyenne_annuelle": "13,61",
      "Resultat Année": "Année Validée" 
    },
    {
      "Nom_complet": "EL ABDI ALAOUI Yassir",
      "Archi Dis": "5,00",
      "Dot_Net": "11,50",
      "Adroide": "8,00",
      "Gest Proj": "11,00",
      "Pr Tutore": "10,00",
      "Data Mining": "12,00",
      "Data Warehouse": "10,00",
      "Moyenne Data Mining et Data Warehouse": "11,00",
      "Resultat Semestre « S2 »": "Semestre « S2 » non Validé",
      "Moyenne S1": "11,08",
      "Moyenne S2": "9,42",
      "Moyenne_annuelle": "10,25",
      "Resultat Année": "Année Validée par Compensation" 
    },
    {
      "Nom_complet": "EL ABDI Omar",
      "Archi Dis": "15,00",
      "Dot_Net": "17,60",
      "Adroide": "15,00",
      "Gest Proj": "11,00",
      "Pr Tutore": "13,25",
      "Data Mining": "12,00",
      "Data Warehouse": "15,17",
      "Moyenne Data Mining et Data Warehouse": "13,59",
      "Resultat Semestre « S2 »": "Validé",
      "Moyenne S1": "15,01",
      "Moyenne S2": "14,24",
      "Moyenne_annuelle": "14,62",
      "Resultat Année": "Année Validée" 
    },
    {
      "Nom_complet": "EL AIDOUNI Hamza",
      "Archi Dis": "7,00",
      "Dot_Net": "13,90",
      "Adroide": "12,00",
      "Gest Proj": "10,00",
      "Pr Tutore": "11,00",
      "Data Mining": "12,00",
      "Data Warehouse": "9,00",
      "Moyenne Data Mining et Data Warehouse": "10,50",
      "Resultat Semestre « S2 »": "Validé avec Compensation",
      "Moyenne S1": "11,50",
      "Moyenne S2": "10,73",
      "Moyenne_annuelle": "11,12",
      "Resultat Année": "Année Validée" 
    },
    {
      "Nom_complet": "EL BADRI Achraf",
      "Archi Dis": "15,00",
      "Dot_Net": "15,00",
      "Adroide": "14,00",
      "Gest Proj": "11,00",
      "Pr Tutore": "14,50",
      "Data Mining": "11,00",
      "Data Warehouse": "10,92",
      "Moyenne Data Mining et Data Warehouse": "10,96",
      "Resultat Semestre « S2 »": "Validé",
      "Moyenne S1": "13,04",
      "Moyenne S2": "13,41",
      "Moyenne_annuelle": "13,23",
      "Resultat Année": "Année Validée" 
    },
    {
      "Nom_complet": "EL FAZAZI Oumayma",
      "Archi Dis": "16,00",
      "Dot_Net": "11,50",
      "Adroide": "12,00",
      "Gest Proj": "13,00",
      "Pr Tutore": "14,00",
      "Data Mining": "13,00",
      "Data Warehouse": "10,00",
      "Moyenne Data Mining et Data Warehouse": "11,50",
      "Resultat Semestre « S2 »": "Validé",
      "Moyenne S1": "14,25",
      "Moyenne S2": "13,00",
      "Moyenne_annuelle": "13,63",
      "Resultat Année": "Année Validée" 
    },
    {
      "Nom_complet": "EL HANTI Wiame",
      "Archi Dis": "16,00",
      "Dot_Net": "15,40",
      "Adroide": "13,00",
      "Gest Proj": "11,00",
      "Pr Tutore": "13,00",
      "Data Mining": "11,00",
      "Data Warehouse": "11,83",
      "Moyenne Data Mining et Data Warehouse": "11,42",
      "Resultat Semestre « S2 »": "Validé",
      "Moyenne S1": "15,25",
      "Moyenne S2": "13,30",
      "Moyenne_annuelle": "14,28",
      "Resultat Année": "Année Validée" 
    },
    {
      "Nom_complet": "EL HASSANI Khadija",
      "Archi Dis": "16,00",
      "Dot_Net": "13,00",
      "Adroide": "11,00",
      "Gest Proj": "11,00",
      "Pr Tutore": "11,00",
      "Data Mining": "11,00",
      "Data Warehouse": "10,17",
      "Moyenne Data Mining et Data Warehouse": "10,59",
      "Resultat Semestre « S2 »": "Validé",
      "Moyenne S1": "13,08",
      "Moyenne S2": "12,10",
      "Moyenne_annuelle": "12,59",
      "Resultat Année": "Année Validée" 
    },
    {
      "Nom_complet": "EL IDRISSI Mourad",
      "Archi Dis": "15,00",
      "Dot_Net": "12,90",
      "Adroide": "14,00",
      "Gest Proj": "11,00",
      "Pr Tutore": "14,00",
      "Data Mining": "12,50",
      "Data Warehouse": "12,42",
      "Moyenne Data Mining et Data Warehouse": "12,46",
      "Resultat Semestre « S2 »": "Validé",
      "Moyenne S1": "12,54",
      "Moyenne S2": "13,23",
      "Moyenne_annuelle": "12,88",
      "Resultat Année": "Année Validée" 
    },
    {
      "Nom_complet": "EL KHADDAR Youness",
      "Archi Dis": "17,00",
      "Dot_Net": "16,60",
      "Adroide": "15,00",
      "Gest Proj": "12,00",
      "Pr Tutore": "15,00",
      "Data Mining": "14,00",
      "Data Warehouse": "13,08",
      "Moyenne Data Mining et Data Warehouse": "13,54",
      "Resultat Semestre « S2 »": "Validé",
      "Moyenne S1": "16,21",
      "Moyenne S2": "14,86",
      "Moyenne_annuelle": "15,53",
      "Resultat Année": "Année Validée" 
    },
    {
      "Nom_complet": "EL MAOUARDY Othman",
      "Archi Dis": "14,00",
      "Dot_Net": "13,80",
      "Adroide": "12,00",
      "Gest Proj": "13,00",
      "Pr Tutore": "16,25",
      "Data Mining": "11,00",
      "Data Warehouse": "12,00",
      "Moyenne Data Mining et Data Warehouse": "11,50",
      "Resultat Semestre « S2 »": "Validé",
      "Moyenne S1": "13,81",
      "Moyenne S2": "13,43",
      "Moyenne_annuelle": "13,62",
      "Resultat Année": "Année Validée" 
    },
    {
      "Nom_complet": "EL TAIEBI Anas",
      "Archi Dis": "5,00",
      "Dot_Net": "12,50",
      "Adroide": "12,00",
      "Gest Proj": "11,00",
      "Pr Tutore": "10,00",
      "Data Mining": "13,00",
      "Data Warehouse": "9,17",
      "Moyenne Data Mining et Data Warehouse": "11,09",
      "Resultat Semestre « S2 »": "Validé avec Compensation",
      "Moyenne S1": "13,00",
      "Moyenne S2": "10,26",
      "Moyenne_annuelle": "11,63",
      "Resultat Année": "Année Validée" 
    },
    {
      "Nom_complet": "EL-HARTY Fatima-Zohra",
      "Archi Dis": "5,00",
      "Dot_Net": "12,00",
      "Adroide": "8,00",
      "Gest Proj": "12,00",
      "Pr Tutore": "13,50",
      "Data Mining": "13,50",
      "Data Warehouse": "12,50",
      "Moyenne Data Mining et Data Warehouse": "13,00",
      "Resultat Semestre « S2 »": "Validé avec Compensation",
      "Moyenne S1": "9,47",
      "Moyenne S2": "10,58",
      "Moyenne_annuelle": "10,03",
      "Resultat Année": "Année Validée par Compensation" 
    },
    {
      "Nom_complet": "ERRIAHI EL IDRISSI Imane",
      "Archi Dis": "2,00",
      "Dot_Net": "11,50",
      "Adroide": "6,00",
      "Gest Proj": "10,00",
      "Pr Tutore": "13,00",
      "Data Mining": "13,00",
      "Data Warehouse": "10,00",
      "Moyenne Data Mining et Data Warehouse": "11,50",
      "Resultat Semestre « S2 »": "Semestre « S2 » non Validé",
      "Moyenne S1": "7,33",
      "Moyenne S2": "9,00",
      "Moyenne_annuelle": "8,17",
      "Resultat Année": "Ajourné" 
    },
    {
      "Nom_complet": "FASSI FEHRI Mohammed",
      "Archi Dis": "14,00",
      "Dot_Net": "13,90",
      "Adroide": "12,00",
      "Gest Proj": "12,00",
      "Pr Tutore": "16,50",
      "Data Mining": "14,00",
      "Data Warehouse": "14,08",
      "Moyenne Data Mining et Data Warehouse": "14,04",
      "Resultat Semestre « S2 »": "Validé",
      "Moyenne S1": "13,72",
      "Moyenne S2": "13,74",
      "Moyenne_annuelle": "13,73",
      "Resultat Année": "Année Validée" 
    },
    {
      "Nom_complet": "FILALI BOUBRAHMI Yassine",
      "Archi Dis": "19,00",
      "Dot_Net": "15,00",
      "Adroide": "16,50",
      "Gest Proj": "11,00",
      "Pr Tutore": "16,75",
      "Data Mining": "11,50",
      "Data Warehouse": "11,58",
      "Moyenne Data Mining et Data Warehouse": "11,54",
      "Resultat Semestre « S2 »": "Validé",
      "Moyenne S1": "17,13",
      "Moyenne S2": "14,97",
      "Moyenne_annuelle": "16,05",
      "Resultat Année": "Année Validée" 
    },
    {
      "Nom_complet": "HABOUZA Nouhaila",
      "Archi Dis": "14,00",
      "Dot_Net": "15,40",
      "Adroide": "13,00",
      "Gest Proj": "15,00",
      "Pr Tutore": "16,00",
      "Data Mining": "13,00",
      "Data Warehouse": "11,83",
      "Moyenne Data Mining et Data Warehouse": "12,42",
      "Resultat Semestre « S2 »": "Validé",
      "Moyenne S1": "14,07",
      "Moyenne S2": "14,30",
      "Moyenne_annuelle": "14,18",
      "Resultat Année": "Année Validée" 
    },
    {
      "Nom_complet": "HAJJAJI Mayssae",
      "Archi Dis": "16,00",
      "Dot_Net": "15,20",
      "Adroide": "14,00",
      "Gest Proj": "15,00",
      "Pr Tutore": "16,00",
      "Data Mining": "14,00",
      "Data Warehouse": "13,58",
      "Moyenne Data Mining et Data Warehouse": "13,79",
      "Resultat Semestre « S2 »": "Validé",
      "Moyenne S1": "15,55",
      "Moyenne S2": "15,00",
      "Moyenne_annuelle": "15,27",
      "Resultat Année": "Année Validée" 
    },
    {
      "Nom_complet": "HAYANI Bouchra",
      "Archi Dis": "15,00",
      "Dot_Net": "11,50",
      "Adroide": "12,00",
      "Gest Proj": "11,00",
      "Pr Tutore": "13,00",
      "Data Mining": "13,00",
      "Data Warehouse": "10,00",
      "Moyenne Data Mining et Data Warehouse": "11,50",
      "Resultat Semestre « S2 »": "Validé",
      "Moyenne S1": "13,17",
      "Moyenne S2": "12,33",
      "Moyenne_annuelle": "12,75",
      "Resultat Année": "Année Validée" 
    },
    {
      "Nom_complet": "HEFIED Anas",
      "Archi Dis": "14,00",
      "Dot_Net": "14,60",
      "Adroide": "13,00",
      "Gest Proj": "12,00",
      "Pr Tutore": "13,50",
      "Data Mining": "11,00",
      "Data Warehouse": "16,17",
      "Moyenne Data Mining et Data Warehouse": "13,59",
      "Resultat Semestre « S2 »": "Validé",
      "Moyenne S1": "13,42",
      "Moyenne S2": "13,45",
      "Moyenne_annuelle": "13,43",
      "Resultat Année": "Année Validée" 
    },
    {
      "Nom_complet": "HOUARI Abdelmoughit",
      "Archi Dis": "16,00",
      "Dot_Net": "15,70",
      "Adroide": "13,00",
      "Gest Proj": "12,00",
      "Pr Tutore": "16,50",
      "Data Mining": "11,00",
      "Data Warehouse": "10,00",
      "Moyenne Data Mining et Data Warehouse": "10,50",
      "Resultat Semestre « S2 »": "Validé",
      "Moyenne S1": "14,28",
      "Moyenne S2": "13,95",
      "Moyenne_annuelle": "14,12",
      "Resultat Année": "Année Validée" 
    },
    {
      "Nom_complet": "IDRISSI KAITOUNI Mohamed Ayoub",
      "Archi Dis": "18,00",
      "Dot_Net": "15,20",
      "Adroide": "14,00",
      "Gest Proj": "14,00",
      "Pr Tutore": "14,00",
      "Data Mining": "14,00",
      "Data Warehouse": "13,00",
      "Moyenne Data Mining et Data Warehouse": "13,50",
      "Resultat Semestre « S2 »": "Validé",
      "Moyenne S1": "16,28",
      "Moyenne S2": "14,78",
      "Moyenne_annuelle": "15,53",
      "Resultat Année": "Année Validée" 
    },
    {
      "Nom_complet": "ISLAHI Oussama",
      "Archi Dis": "16,00",
      "Dot_Net": "13,50",
      "Adroide": "12,00",
      "Gest Proj": "12,00",
      "Pr Tutore": "14,00",
      "Data Mining": "14,00",
      "Data Warehouse": "12,67",
      "Moyenne Data Mining et Data Warehouse": "13,34",
      "Resultat Semestre « S2 »": "Validé",
      "Moyenne S1": "14,77",
      "Moyenne S2": "13,47",
      "Moyenne_annuelle": "14,12",
      "Resultat Année": "Année Validée" 
    },
    {
      "Nom_complet": "JABBOUR Ahmed",
      "Archi Dis": "16,00",
      "Dot_Net": "9,00",
      "Adroide": "15,00",
      "Gest Proj": "14,00",
      "Pr Tutore": "13,50",
      "Data Mining": "18,00",
      "Data Warehouse": "16,42",
      "Moyenne Data Mining et Data Warehouse": "17,21",
      "Resultat Semestre « S2 »": "Validé avec Compensation",
      "Moyenne S1": "13,08",
      "Moyenne S2": "14,12",
      "Moyenne_annuelle": "13,60",
      "Resultat Année": "Année Validée" 
    },
    {
      "Nom_complet": "JANATI IDRISSI Youssef",
      "Archi Dis": "16,00",
      "Dot_Net": "16,00",
      "Adroide": "15,00",
      "Gest Proj": "11,00",
      "Pr Tutore": "13,00",
      "Data Mining": "15,00",
      "Data Warehouse": "15,33",
      "Moyenne Data Mining et Data Warehouse": "15,17",
      "Resultat Semestre « S2 »": "Validé",
      "Moyenne S1": "15,00",
      "Moyenne S2": "14,36",
      "Moyenne_annuelle": "14,68",
      "Resultat Année": "Année Validée" 
    },
    {
      "Nom_complet": "KADIRI Kenza",
      "Archi Dis": "15,00",
      "Dot_Net": "15,60",
      "Adroide": "13,00",
      "Gest Proj": "12,00",
      "Pr Tutore": "12,00",
      "Data Mining": "13,00",
      "Data Warehouse": "15,00",
      "Moyenne Data Mining et Data Warehouse": "14,00",
      "Resultat Semestre « S2 »": "Validé",
      "Moyenne S1": "13,67",
      "Moyenne S2": "13,60",
      "Moyenne_annuelle": "13,63",
      "Resultat Année": "Année Validée" 
    },
    {
      "Nom_complet": "KAMARI Mohammed",
      "Archi Dis": "16,00",
      "Dot_Net": "13,40",
      "Adroide": "16,00",
      "Gest Proj": "15,00",
      "Pr Tutore": "16,25",
      "Data Mining": "17,00",
      "Data Warehouse": "12,08",
      "Moyenne Data Mining et Data Warehouse": "14,54",
      "Resultat Semestre « S2 »": "Validé",
      "Moyenne S1": "15,29",
      "Moyenne S2": "15,20",
      "Moyenne_annuelle": "15,25",
      "Resultat Année": "Année Validée" 
    },
    {
      "Nom_complet": "KERROUM Jihane",
      "Archi Dis": "16,00",
      "Dot_Net": "16,80",
      "Adroide": "14,00",
      "Gest Proj": "17,00",
      "Pr Tutore": "20,00",
      "Data Mining": "17,00",
      "Data Warehouse": "14,67",
      "Moyenne Data Mining et Data Warehouse": "15,84",
      "Resultat Semestre « S2 »": "Validé",
      "Moyenne S1": "16,64",
      "Moyenne S2": "16,61",
      "Moyenne_annuelle": "16,62",
      "Resultat Année": "Année Validée" 
    },
    {
      "Nom_complet": "KFAL Youssef",
      "Archi Dis": "14,00",
      "Dot_Net": "15,60",
      "Adroide": "13,00",
      "Gest Proj": "11,00",
      "Pr Tutore": "16,50",
      "Data Mining": "11,00",
      "Data Warehouse": "12,17",
      "Moyenne Data Mining et Data Warehouse": "11,59",
      "Resultat Semestre « S2 »": "Validé",
      "Moyenne S1": "12,84",
      "Moyenne S2": "13,61",
      "Moyenne_annuelle": "13,23",
      "Resultat Année": "Année Validée" 
    },
    {
      "Nom_complet": "KHADDOURI Achraf",
      "Archi Dis": "19,00",
      "Dot_Net": "17,40",
      "Adroide": "16,00",
      "Gest Proj": "14,00",
      "Pr Tutore": "20,00",
      "Data Mining": "15,00",
      "Data Warehouse": "10,00",
      "Moyenne Data Mining et Data Warehouse": "12,50",
      "Resultat Semestre « S2 »": "Validé",
      "Moyenne S1": "16,00",
      "Moyenne S2": "16,48",
      "Moyenne_annuelle": "16,24",
      "Resultat Année": "Année Validée" 
    },
    {
      "Nom_complet": "LAANAYA Youssef",
      "Archi Dis": "5,00",
      "Dot_Net": "11,00",
      "Adroide": "8,00",
      "Gest Proj": "10,00",
      "Pr Tutore": "10,00",
      "Data Mining": "13,00",
      "Data Warehouse": "9,00",
      "Moyenne Data Mining et Data Warehouse": "11,00",
      "Resultat Semestre « S2 »": "Semestre « S2 » non Validé",
      "Moyenne S1": "6,72",
      "Moyenne S2": "9,17",
      "Moyenne_annuelle": "7,94",
      "Resultat Année": "Ajourné" 
    },
    {
      "Nom_complet": "LABSAILI Zidane",
      "Archi Dis": "10,00",
      "Dot_Net": "11,00",
      "Adroide": "10,00",
      "Gest Proj": "11,00",
      "Pr Tutore": "12,50",
      "Data Mining": "13,00",
      "Data Warehouse": "9,00",
      "Moyenne Data Mining et Data Warehouse": "11,00",
      "Resultat Semestre « S2 »": "Validé",
      "Moyenne S1": "9,30",
      "Moyenne S2": "10,92",
      "Moyenne_annuelle": "10,11",
      "Resultat Année": "Année Validée par Compensation" 
    },
    {
      "Nom_complet": "LACHKAR  El Hassan",
      "Archi Dis": "17,00",
      "Dot_Net": "17,60",
      "Adroide": "19,00",
      "Gest Proj": "15,00",
      "Pr Tutore": "15,00",
      "Data Mining": "14,00",
      "Data Warehouse": "15,50",
      "Moyenne Data Mining et Data Warehouse": "14,75",
      "Resultat Semestre « S2 »": "Validé",
      "Moyenne S1": "17,32",
      "Moyenne S2": "16,39",
      "Moyenne_annuelle": "16,85",
      "Resultat Année": "Année Validée" 
    },
    {
      "Nom_complet": "LAHTANI Iliass",
      "Archi Dis": "15,00",
      "Dot_Net": "12,00",
      "Adroide": "12,00",
      "Gest Proj": "11,00",
      "Pr Tutore": "14,00",
      "Data Mining": "11,00",
      "Data Warehouse": "18,00",
      "Moyenne Data Mining et Data Warehouse": "14,50",
      "Resultat Semestre « S2 »": "Validé",
      "Moyenne S1": "14,00",
      "Moyenne S2": "13,08",
      "Moyenne_annuelle": "13,54",
      "Resultat Année": "Année Validée" 
    },
    {
      "Nom_complet": "LAKHAL SENHAJI Hanae",
      "Archi Dis": "15,00",
      "Dot_Net": "14,60",
      "Adroide": "15,00",
      "Gest Proj": "12,00",
      "Pr Tutore": "14,00",
      "Data Mining": "14,00",
      "Data Warehouse": "10,00",
      "Moyenne Data Mining et Data Warehouse": "12,00",
      "Resultat Semestre « S2 »": "Validé",
      "Moyenne S1": "13,40",
      "Moyenne S2": "13,77",
      "Moyenne_annuelle": "13,58",
      "Resultat Année": "Année Validée" 
    },
    {
      "Nom_complet": "LARAICH Abir",
      "Archi Dis": "14,00",
      "Dot_Net": "13,80",
      "Adroide": "12,00",
      "Gest Proj": "15,00",
      "Pr Tutore": "15,00",
      "Data Mining": "16,00",
      "Data Warehouse": "13,25",
      "Moyenne Data Mining et Data Warehouse": "14,63",
      "Resultat Semestre « S2 »": "Validé",
      "Moyenne S1": "14,01",
      "Moyenne S2": "14,07",
      "Moyenne_annuelle": "14,04",
      "Resultat Année": "Année Validée" 
    },
    {
      "Nom_complet": "LAYADI Amine",
      "Archi Dis": "17,00",
      "Dot_Net": "15,20",
      "Adroide": "14,00",
      "Gest Proj": "13,00",
      "Pr Tutore": "13,50",
      "Data Mining": "11,00",
      "Data Warehouse": "10,83",
      "Moyenne Data Mining et Data Warehouse": "10,92",
      "Resultat Semestre « S2 »": "Validé",
      "Moyenne S1": "14,20",
      "Moyenne S2": "13,94",
      "Moyenne_annuelle": "14,07",
      "Resultat Année": "Année Validée" 
    },
    {
      "Nom_complet": "MAFDOULI Ayman",
      "Archi Dis": "13,00",
      "Dot_Net": "14,20",
      "Adroide": "14,00",
      "Gest Proj": "14,00",
      "Pr Tutore": "14,75",
      "Data Mining": "12,00",
      "Data Warehouse": "13,17",
      "Moyenne Data Mining et Data Warehouse": "12,59",
      "Resultat Semestre « S2 »": "Validé",
      "Moyenne S1": "13,43",
      "Moyenne S2": "13,76",
      "Moyenne_annuelle": "13,59",
      "Resultat Année": "Année Validée" 
    },
    {
      "Nom_complet": "MAHOU Mohamed EL Mehdi",
      "Archi Dis": "17,00",
      "Dot_Net": "14,00",
      "Adroide": "19,00",
      "Gest Proj": "12,00",
      "Pr Tutore": "14,25",
      "Data Mining": "12,00",
      "Data Warehouse": "11,17",
      "Moyenne Data Mining et Data Warehouse": "11,59",
      "Resultat Semestre « S2 »": "Validé",
      "Moyenne S1": "15,11",
      "Moyenne S2": "14,64",
      "Moyenne_annuelle": "14,87",
      "Resultat Année": "Année Validée" 
    },
    {
      "Nom_complet": "MANCHOUD Ghita",
      "Archi Dis": "12,00",
      "Dot_Net": "15,00",
      "Adroide": "14,00",
      "Gest Proj": "12,00",
      "Pr Tutore": "14,75",
      "Data Mining": "11,00",
      "Data Warehouse": "12,00",
      "Moyenne Data Mining et Data Warehouse": "11,50",
      "Resultat Semestre « S2 »": "Validé",
      "Moyenne S1": "13,12",
      "Moyenne S2": "13,21",
      "Moyenne_annuelle": "13,16",
      "Resultat Année": "Année Validée" 
    },
    {
      "Nom_complet": "MEZZOUR Ghita",
      "Archi Dis": "15,00",
      "Dot_Net": "14,60",
      "Adroide": "14,00",
      "Gest Proj": "14,00",
      "Pr Tutore": "13,75",
      "Data Mining": "14,00",
      "Data Warehouse": "14,67",
      "Moyenne Data Mining et Data Warehouse": "14,34",
      "Resultat Semestre « S2 »": "Validé",
      "Moyenne S1": "14,44",
      "Moyenne S2": "14,28",
      "Moyenne_annuelle": "14,36",
      "Resultat Année": "Année Validée" 
    },
    {
      "Nom_complet": "MKASSI Chaymae",
      "Archi Dis": "18,00",
      "Dot_Net": "15,00",
      "Adroide": "15,00",
      "Gest Proj": "12,00",
      "Pr Tutore": "15,00",
      "Data Mining": "11,00",
      "Data Warehouse": "14,50",
      "Moyenne Data Mining et Data Warehouse": "12,75",
      "Resultat Semestre « S2 »": "Validé",
      "Moyenne S1": "15,58",
      "Moyenne S2": "14,63",
      "Moyenne_annuelle": "15,10",
      "Resultat Année": "Année Validée" 
    },
    {
      "Nom_complet": "MOUTAOUAKEL Mohamed Yassine",
      "Archi Dis": "12,00",
      "Dot_Net": "12,50",
      "Adroide": "12,00",
      "Gest Proj": "11,00",
      "Pr Tutore": "11,00",
      "Data Mining": "11,00",
      "Data Warehouse": "10,00",
      "Moyenne Data Mining et Data Warehouse": "10,50",
      "Resultat Semestre « S2 »": "Validé",
      "Moyenne S1": "12,50",
      "Moyenne S2": "11,50",
      "Moyenne_annuelle": "12,00",
      "Resultat Année": "Année Validée" 
    },
    {
      "Nom_complet": "OUALI ALAMI Salma",
      "Archi Dis": "17,00",
      "Dot_Net": "17,60",
      "Adroide": "15,00",
      "Gest Proj": "15,00",
      "Pr Tutore": "15,25",
      "Data Mining": "15,00",
      "Data Warehouse": "14,92",
      "Moyenne Data Mining et Data Warehouse": "14,96",
      "Resultat Semestre « S2 »": "Validé",
      "Moyenne S1": "17,40",
      "Moyenne S2": "15,80",
      "Moyenne_annuelle": "16,60",
      "Resultat Année": "Année Validée" 
    },
    {
      "Nom_complet": "OUFKIR Mounat",
      "Archi Dis": "14,00",
      "Dot_Net": "13,00",
      "Adroide": "12,00",
      "Gest Proj": "17,00",
      "Pr Tutore": "14,00",
      "Data Mining": "15,00",
      "Data Warehouse": "11,42",
      "Moyenne Data Mining et Data Warehouse": "13,21",
      "Resultat Semestre « S2 »": "Validé",
      "Moyenne S1": "13,10",
      "Moyenne S2": "13,87",
      "Moyenne_annuelle": "13,48",
      "Resultat Année": "Année Validée" 
    },
    {
      "Nom_complet": "OUHANNOU Othman",
      "Archi Dis": "15,00",
      "Dot_Net": "12,90",
      "Adroide": "14,00",
      "Gest Proj": "14,00",
      "Pr Tutore": "16,00",
      "Data Mining": "14,00",
      "Data Warehouse": "12,92",
      "Moyenne Data Mining et Data Warehouse": "13,46",
      "Resultat Semestre « S2 »": "Validé",
      "Moyenne S1": "12,78",
      "Moyenne S2": "14,23",
      "Moyenne_annuelle": "13,51",
      "Resultat Année": "Année Validée" 
    },
    {
      "Nom_complet": "OUMOUSSI Abderrahim",
      "Archi Dis": "15,00",
      "Dot_Net": "15,20",
      "Adroide": "14,00",
      "Gest Proj": "11,00",
      "Pr Tutore": "17,00",
      "Data Mining": "11,00",
      "Data Warehouse": "11,00",
      "Moyenne Data Mining et Data Warehouse": "11,00",
      "Resultat Semestre « S2 »": "Validé",
      "Moyenne S1": "15,71",
      "Moyenne S2": "13,87",
      "Moyenne_annuelle": "14,79",
      "Resultat Année": "Année Validée" 
    },
    {
      "Nom_complet": "RATAYL Zakaria",
      "Archi Dis": "16,00",
      "Dot_Net": "12,00",
      "Adroide": "14,00",
      "Gest Proj": "11,00",
      "Pr Tutore": "12,50",
      "Data Mining": "11,00",
      "Data Warehouse": "12,00",
      "Moyenne Data Mining et Data Warehouse": "11,50",
      "Resultat Semestre « S2 »": "Validé",
      "Moyenne S1": "13,72",
      "Moyenne S2": "12,83",
      "Moyenne_annuelle": "13,28",
      "Resultat Année": "Année Validée" 
    },
    {
      "Nom_complet": "REGRAGUI Yasmine",
      "Archi Dis": "15,00",
      "Dot_Net": "16,80",
      "Adroide": "13,00",
      "Gest Proj": "14,00",
      "Pr Tutore": "15,50",
      "Data Mining": "13,00",
      "Data Warehouse": "10,00",
      "Moyenne Data Mining et Data Warehouse": "11,50",
      "Resultat Semestre « S2 »": "Validé",
      "Moyenne S1": "14,38",
      "Moyenne S2": "14,30",
      "Moyenne_annuelle": "14,34",
      "Resultat Année": "Année Validée" 
    },
    {
      "Nom_complet": "ROBIO Imane",
      "Archi Dis": "16,00",
      "Dot_Net": "15,20",
      "Adroide": "14,00",
      "Gest Proj": "13,00",
      "Pr Tutore": "13,50",
      "Data Mining": "15,00",
      "Data Warehouse": "12,50",
      "Moyenne Data Mining et Data Warehouse": "13,75",
      "Resultat Semestre « S2 »": "Validé",
      "Moyenne S1": "14,49",
      "Moyenne S2": "14,24",
      "Moyenne_annuelle": "14,37",
      "Resultat Année": "Année Validée" 
    },
    {
      "Nom_complet": "SABER Al Mehdi",
      "Archi Dis": "16,00",
      "Dot_Net": "16,60",
      "Adroide": "19,00",
      "Gest Proj": "10,00",
      "Pr Tutore": "15,50",
      "Data Mining": "12,00",
      "Data Warehouse": "14,58",
      "Moyenne Data Mining et Data Warehouse": "13,29",
      "Resultat Semestre « S2 »": "Validé",
      "Moyenne S1": "13,21",
      "Moyenne S2": "15,07",
      "Moyenne_annuelle": "14,14",
      "Resultat Année": "Année Validée" 
    },
    {
      "Nom_complet": "SATORI Najwa",
      "Archi Dis": "14,00",
      "Dot_Net": "15,20",
      "Adroide": "12,00",
      "Gest Proj": "15,00",
      "Pr Tutore": "14,00",
      "Data Mining": "13,00",
      "Data Warehouse": "12,43",
      "Moyenne Data Mining et Data Warehouse": "12,72",
      "Resultat Semestre « S2 »": "Validé",
      "Moyenne S1": "14,18",
      "Moyenne S2": "13,82",
      "Moyenne_annuelle": "14,00",
      "Resultat Année": "Année Validée" 
    },
    {
      "Nom_complet": "SGHOURI Salma",
      "Archi Dis": "15,00",
      "Dot_Net": "16,00",
      "Adroide": "12,00",
      "Gest Proj": "12,00",
      "Pr Tutore": "12,50",
      "Data Mining": "16,00",
      "Data Warehouse": "12,50",
      "Moyenne Data Mining et Data Warehouse": "14,25",
      "Resultat Semestre « S2 »": "Validé",
      "Moyenne S1": "14,58",
      "Moyenne S2": "13,63",
      "Moyenne_annuelle": "14,10",
      "Resultat Année": "Année Validée" 
    },
    {
      "Nom_complet": "SMYAJ Abdelhakim",
      "Archi Dis": "16,00",
      "Dot_Net": "16,60",
      "Adroide": "13,00",
      "Gest Proj": "11,00",
      "Pr Tutore": "19,50",
      "Data Mining": "13,00",
      "Data Warehouse": "11,08",
      "Moyenne Data Mining et Data Warehouse": "12,04",
      "Resultat Semestre « S2 »": "Validé",
      "Moyenne S1": "16,43",
      "Moyenne S2": "14,69",
      "Moyenne_annuelle": "15,56",
      "Resultat Année": "Année Validée" 
    },
    {
      "Nom_complet": "TELMEM Mehdi",
      "Archi Dis": "16,00",
      "Dot_Net": "16,80",
      "Adroide": "14,00",
      "Gest Proj": "14,00",
      "Pr Tutore": "16,50",
      "Data Mining": "17,00",
      "Data Warehouse": "14,58",
      "Moyenne Data Mining et Data Warehouse": "15,79",
      "Resultat Semestre « S2 »": "Validé",
      "Moyenne S1": "15,59",
      "Moyenne S2": "15,52",
      "Moyenne_annuelle": "15,55",
      "Resultat Année": "Année Validée" 
    },
    {
      "Nom_complet": "TIRAOUI Mohamed Soufiane",
      "Archi Dis": "17,00",
      "Dot_Net": "13,60",
      "Adroide": "12,00",
      "Gest Proj": "11,00",
      "Pr Tutore": "11,00",
      "Data Mining": "11,00",
      "Data Warehouse": "10,00",
      "Moyenne Data Mining et Data Warehouse": "10,50",
      "Resultat Semestre « S2 »": "Validé",
      "Moyenne S1": "14,59",
      "Moyenne S2": "12,52",
      "Moyenne_annuelle": "13,55",
      "Resultat Année": "Année Validée" 
    },
    {
      "Nom_complet": "ZAADOUD Marouane",
      "Archi Dis": "2,00",
      "Dot_Net": "11,00",
      "Adroide": "8,00",
      "Gest Proj": "10,00",
      "Pr Tutore": "11,00",
      "Data Mining": "11,00",
      "Data Warehouse": "6,00",
      "Moyenne Data Mining et Data Warehouse": "8,50",
      "Resultat Semestre « S2 »": "Semestre « S2 » non Validé",
      "Moyenne S1": "7,33",
      "Moyenne S2": "8,42",
      "Moyenne_annuelle": "7,88",
      "Resultat Année": "Ajourné" 
    },
    {
      "Nom_complet": "ZAHRAOUI Imane",
      "Archi Dis": "19,00",
      "Dot_Net": "17,70",
      "Adroide": "18,00",
      "Gest Proj": "14,00",
      "Pr Tutore": "16,75",
      "Data Mining": "14,00",
      "Data Warehouse": "15,50",
      "Moyenne Data Mining et Data Warehouse": "14,75",
      "Resultat Semestre « S2 »": "Validé",
      "Moyenne S1": "17,50",
      "Moyenne S2": "16,70",
      "Moyenne_annuelle": "17,10",
      "Resultat Année": "Année Validée" 
    },
    {
      "Nom_complet": "ZOLATI Soukaina",
      "Archi Dis": "18,00",
      "Dot_Net": "15,40",
      "Adroide": "13,00",
      "Gest Proj": "13,00",
      "Pr Tutore": "13,25",
      "Data Mining": "12,00",
      "Data Warehouse": "11,42",
      "Moyenne Data Mining et Data Warehouse": "11,71",
      "Resultat Semestre « S2 »": "Validé",
      "Moyenne S1": "16,28",
      "Moyenne S2": "14,06",
      "Moyenne_annuelle": "15,17",
      "Resultat Année": "Année Validée" 
    }
  ]